configs/logistic_config.json
configs/rf_config.json
configs/svm_config.json
configs/tf_cnn_config.json
configs/tf_dnn_config.json
configs/tf_rnn_config.json
configs/tune_logistic_config.json
configs/tune_rf_config.json
configs/tune_svm_config.json
configs/tune_xgb_config.json
configs/xgb_config.json
mlcli/__init__.py
mlcli/__main__.py
mlcli/cli.py
mlcli/automl/__init__.py
mlcli/automl/base_automl.py
mlcli/automl/model_selector.py
mlcli/automl/search_space.py
mlcli/config/__init__.py
mlcli/config/loader.py
mlcli/explainer/__init__.py
mlcli/explainer/base_explainer.py
mlcli/explainer/explainer_factory.py
mlcli/explainer/lime_explainer.py
mlcli/explainer/shap_explainer.py
mlcli/preprocessor/__init__.py
mlcli/preprocessor/base_preprocessor.py
mlcli/preprocessor/encoders.py
mlcli/preprocessor/feature_selectors.py
mlcli/preprocessor/normalizers.py
mlcli/preprocessor/pipeline.py
mlcli/preprocessor/preprocessor_factory.py
mlcli/preprocessor/scalers.py
mlcli/runner/__init__.py
mlcli/runner/experiment_tracker.py
mlcli/trainers/__init__.py
mlcli/trainers/base_trainer.py
mlcli/trainers/catboost_trainer.py
mlcli/trainers/lightgbm_trainer.py
mlcli/trainers/logistic_trainer.py
mlcli/trainers/rf_trainer.py
mlcli/trainers/svm_trainer.py
mlcli/trainers/tf_cnn_trainer.py
mlcli/trainers/tf_dnn_trainer.py
mlcli/trainers/tf_rnn_trainer.py
mlcli/trainers/xgb_trainer.py
mlcli/trainers/anomaly/__init__.py
mlcli/trainers/anomaly/isolation_forest_trainer.py
mlcli/trainers/anomaly/one_class_svm_trainer.py
mlcli/trainers/clustering/__init__.py
mlcli/trainers/clustering/dbscan_trainer.py
mlcli/trainers/clustering/kmeans_trainer.py
mlcli/tuner/__init__.py
mlcli/tuner/base_tuner.py
mlcli/tuner/grid_tuner.py
mlcli/tuner/optuna_tuner.py
mlcli/tuner/random_tuner.py
mlcli/tuner/tuner_factory.py
mlcli/ui/__init__.py
mlcli/ui/app.py
mlcli/ui/screens/__init__.py
mlcli/ui/widgets/__init__.py
mlcli/utils/__init__.py
mlcli/utils/io.py
mlcli/utils/logger.py
mlcli/utils/metrics.py
mlcli/utils/registry.py
mlcli_toolkit-0.3.1.dist-info/licenses/LICENSE
mlcli_toolkit-0.3.1.dist-info/METADATA
mlcli_toolkit-0.3.1.dist-info/WHEEL
mlcli_toolkit-0.3.1.dist-info/entry_points.txt
mlcli_toolkit-0.3.1.dist-info/top_level.txt
mlcli_toolkit-0.3.1.dist-info/RECORD
