Metadata-Version: 2.4
Name: mlcli-toolkit
Version: 0.3.1
Summary: A production-ready CLI toolkit for training, evaluating, and tracking Machine Learning and Deep Learning models with experiment tracking, hyperparameter tuning, model explainability, and an interactive TUI
Author-email: Devarshi Lalani <devarshilalani.devflow@gmail.com>
License: MIT
Project-URL: Homepage, https://github.com/codeMaestro78/MLcli
Project-URL: Documentation, https://github.com/codeMaestro78/MLcli#readme
Project-URL: Repository, https://github.com/codeMaestro78/MLcli
Project-URL: Issues, https://github.com/codeMaestro78/MLcli/issues
Keywords: machine-learning,deep-learning,cli,mlops,experiment-tracking,hyperparameter-tuning,model-training,scikit-learn,tensorflow,xgboost
Classifier: Development Status :: 4 - Beta
Classifier: Intended Audience :: Developers
Classifier: Intended Audience :: Science/Research
Classifier: Intended Audience :: Education
Classifier: Intended Audience :: Information Technology
Classifier: Natural Language :: English
Classifier: Operating System :: OS Independent
Classifier: License :: OSI Approved :: MIT License
Classifier: Programming Language :: Python :: 3
Classifier: Programming Language :: Python :: 3.10
Classifier: Programming Language :: Python :: 3.11
Classifier: Programming Language :: Python :: 3.12
Classifier: Programming Language :: Python :: 3.13
Classifier: Topic :: Scientific/Engineering
Classifier: Topic :: Scientific/Engineering :: Artificial Intelligence
Classifier: Environment :: Console
Classifier: Typing :: Typed
Requires-Python: >=3.10
License-File: LICENSE
Requires-Dist: joblib>=1.1
Requires-Dist: numpy<2.0,>=1.24
Requires-Dist: onnx>=1.14
Requires-Dist: onnxruntime>=1.15
Requires-Dist: pandas>=2.0
Requires-Dist: plotext>=5.0
Requires-Dist: pyyaml>=6.0
Requires-Dist: rich-click>=1.6.0
Requires-Dist: scikit-learn>=1.0
Requires-Dist: skl2onnx>=1.14
Requires-Dist: tensorflow>=2.10
Requires-Dist: textual>=0.40.0
Requires-Dist: typer[all]>=0.7.0
Requires-Dist: xgboost>=1.7
Requires-Dist: lightgbm>=4.0.0
Requires-Dist: catboost>=1.2.0
Requires-Dist: statsmodels>=0.14.0
Requires-Dist: prophet>=1.1.0
Provides-Extra: dev
Requires-Dist: pytest>=9.0; extra == "dev"
Requires-Dist: pytest-cov>=7.0; extra == "dev"
Requires-Dist: black>=25.0; extra == "dev"
Requires-Dist: flake8>=7.0; extra == "dev"
Requires-Dist: mypy>=1.0; extra == "dev"
Dynamic: license-file
